LICENSE.txt
README.md
setup.py
rocketpkg1/__init__.py
rocketpkg1/rocketpkg1.py
rocketpkg1.egg-info/PKG-INFO
rocketpkg1.egg-info/SOURCES.txt
rocketpkg1.egg-info/dependency_links.txt
rocketpkg1.egg-info/top_level.txt