Metadata-Version: 2.1
Name: rocketpkg1
Version: 1.0.0
Summary: An awesome package that does something
Home-page: http://pypi.python.org/pypi/rocketpkg1lib/
Author: abdelillah
Author-email: abdelilah2003@gmail.com
License: LICENSE.txt
License-File: LICENSE.txt
